cms/__init__.py
cms/main.py
cms/cli/__init__.py
cms/cli/cms_data.py
cms/commands/__init__.py
cms/commands/cms_data.py
cms/core/__init__.py
cms/core/enums.py
cms/core/interpolation.py
cms/core/magdircalculator.py
cms/core/utils.py
cms_cli-0.0.1.dist-info/licenses/LICENCE.md
cms_cli-0.0.1.dist-info/METADATA
cms_cli-0.0.1.dist-info/WHEEL
cms_cli-0.0.1.dist-info/entry_points.txt
cms_cli-0.0.1.dist-info/top_level.txt
cms_cli-0.0.1.dist-info/RECORD
