Metadata-Version: 2.4
Name: cms-cli
Version: 0.0.1
Summary: A cli for downloading and converting Copernicus Marine Service datasets to GeoTIFFs
Author-email: Moritz Steinsiek <steinsiek@eomap.de>
License: CC-BY-NC-4.0
Project-URL: Homepage, https://www.eomap.com
Keywords: copernicus,marine,geotiff,oceanography,satellite-data,earth-observation,cli
Classifier: Development Status :: 4 - Beta
Classifier: Intended Audience :: Science/Research
Classifier: Intended Audience :: Developers
Classifier: License :: Other/Proprietary License
Classifier: Programming Language :: Python :: 3
Classifier: Programming Language :: Python :: 3.12
Classifier: Programming Language :: Python :: 3.13
Classifier: Topic :: Scientific/Engineering :: GIS
Classifier: Topic :: Scientific/Engineering :: Oceanography
Classifier: Environment :: Console
Classifier: Operating System :: OS Independent
Requires-Python: >=3.12
License-File: LICENCE.md
Requires-Dist: copernicusmarine>=2.0.0
Requires-Dist: python-dotenv>=1.0.1
Requires-Dist: rasterio>=1.4.3
Requires-Dist: geopandas>=1.0.1
Requires-Dist: scipy>=1.16.3
Requires-Dist: pandas-stubs~=2.3.3
Dynamic: license-file
